{
    "/js/app.js": "/js/app.js?id=f96cc4b600724898c813",
    "/css/app.css": "/css/app.css?id=065bf575493c4cf83de4",
    "/js/chunks/94d3cc480aecbb9c0e0a.js": "/js/chunks/94d3cc480aecbb9c0e0a.js?id=f66c1145c873f8c79079",
    "/js/chunks/d181058674651fa054ba.js": "/js/chunks/d181058674651fa054ba.js?id=76e4bd19d3b7678f3b0f",
    "/js/chunks/9828e41203f4257ae33d.js": "/js/chunks/9828e41203f4257ae33d.js?id=dbd2f1724bcb31e6e73b",
    "/js/chunks/b54250c5628cff2aea02.js": "/js/chunks/b54250c5628cff2aea02.js?id=075aab1ce6075a081f8d",
    "/js/chunks/d9fbc6e615ff3a0eb69a.js": "/js/chunks/d9fbc6e615ff3a0eb69a.js?id=dee9966e41a94c038fba",
    "/js/chunks/11fe771077ef093573d1.js": "/js/chunks/11fe771077ef093573d1.js?id=c21eeee70d2c67509593",
    "/js/chunks/14d0a364a8d786f95877.js": "/js/chunks/14d0a364a8d786f95877.js?id=bd4396941c847b15a051",
    "/js/chunks/fefd7f127e3f0ccbf311.js": "/js/chunks/fefd7f127e3f0ccbf311.js?id=e7a99ceae8184d42ac05",
    "/js/chunks/73aa93e4a044185a1431.js": "/js/chunks/73aa93e4a044185a1431.js?id=787fa93b8ce4819906dd",
    "/js/chunks/6bfa1e563630f555c84a.js": "/js/chunks/6bfa1e563630f555c84a.js?id=b605d98aec7a09351b3b",
    "/js/chunks/10686cae8fae95313b6c.js": "/js/chunks/10686cae8fae95313b6c.js?id=34165ca377bdce844ad6",
    "/js/chunks/1ff2f3c22691d3cd9cb9.js": "/js/chunks/1ff2f3c22691d3cd9cb9.js?id=b69d8cc76697fad1887e",
    "/js/chunks/50bfe4440e6fc7b80c3a.js": "/js/chunks/50bfe4440e6fc7b80c3a.js?id=4ebdfcfe499952f645c1",
    "/js/chunks/1027767e20a7eccaea2c.js": "/js/chunks/1027767e20a7eccaea2c.js?id=7ee3ff15cdba7b913fa6",
    "/js/chunks/0303425b6808c35c3302.js": "/js/chunks/0303425b6808c35c3302.js?id=8d8510b852b35ac7a35f",
    "/js/chunks/869fff49a95ff6f25cec.js": "/js/chunks/869fff49a95ff6f25cec.js?id=7b04b8174f8beffba0e3",
    "/js/chunks/002795a40a9935934e8f.js": "/js/chunks/002795a40a9935934e8f.js?id=d4006b8c2e82da1ae3cc",
    "/js/chunks/6710b689a3f9cb3c14c0.js": "/js/chunks/6710b689a3f9cb3c14c0.js?id=6ce30979ec1b7b4c260f",
    "/js/chunks/ba9a4d78cf0d06dfa3a7.js": "/js/chunks/ba9a4d78cf0d06dfa3a7.js?id=16873e0b65b89eeff427",
    "/js/chunks/c0b02a97dc4c577ee2dc.js": "/js/chunks/c0b02a97dc4c577ee2dc.js?id=08bcd8e424e65d78bd27",
    "/js/chunks/3f1bdcefafb85f9978fc.js": "/js/chunks/3f1bdcefafb85f9978fc.js?id=87c12569243ab0c7a172",
    "/js/chunks/c1b2fb547814bac9ac84.js": "/js/chunks/c1b2fb547814bac9ac84.js?id=f66c1145c873f8c79079",
    "/js/chunks/eebf72d61fb3480addfe.js": "/js/chunks/eebf72d61fb3480addfe.js?id=dbd2f1724bcb31e6e73b",
    "/js/chunks/54b99cc54717813bb551.js": "/js/chunks/54b99cc54717813bb551.js?id=dee9966e41a94c038fba",
    "/js/chunks/0fb2ed54f889e0403ef8.js": "/js/chunks/0fb2ed54f889e0403ef8.js?id=787fa93b8ce4819906dd",
    "/js/chunks/eae7ca73e3487309a0ba.js": "/js/chunks/eae7ca73e3487309a0ba.js?id=b605d98aec7a09351b3b",
    "/js/chunks/7bf66ed375ec6ae7333f.js": "/js/chunks/7bf66ed375ec6ae7333f.js?id=f66c1145c873f8c79079",
    "/js/chunks/eea03625ebb4c4d5b6f9.js": "/js/chunks/eea03625ebb4c4d5b6f9.js?id=dbd2f1724bcb31e6e73b",
    "/js/chunks/7eb8ea43d4cc31ca5419.js": "/js/chunks/7eb8ea43d4cc31ca5419.js?id=dee9966e41a94c038fba",
    "/js/chunks/1b1afec4831b1e0501ab.js": "/js/chunks/1b1afec4831b1e0501ab.js?id=787fa93b8ce4819906dd",
    "/js/chunks/1f3b70ea330fccd9772f.js": "/js/chunks/1f3b70ea330fccd9772f.js?id=b605d98aec7a09351b3b",
    "/js/chunks/aa806eaa7bd53139ed38.js": "/js/chunks/aa806eaa7bd53139ed38.js?id=f66c1145c873f8c79079",
    "/js/chunks/427d043f799a0179ec09.js": "/js/chunks/427d043f799a0179ec09.js?id=dbd2f1724bcb31e6e73b",
    "/js/chunks/d19bc772b90af4cc8f14.js": "/js/chunks/d19bc772b90af4cc8f14.js?id=dee9966e41a94c038fba",
    "/js/chunks/3ac600172ebe98f4a363.js": "/js/chunks/3ac600172ebe98f4a363.js?id=787fa93b8ce4819906dd",
    "/js/chunks/5c02c1ece5c9656d9800.js": "/js/chunks/5c02c1ece5c9656d9800.js?id=b605d98aec7a09351b3b",
    "/js/chunks/47cb8012ec60d08d7130.js": "/js/chunks/47cb8012ec60d08d7130.js?id=f66c1145c873f8c79079",
    "/js/chunks/ed2045dc1dc45df6e0aa.js": "/js/chunks/ed2045dc1dc45df6e0aa.js?id=dbd2f1724bcb31e6e73b",
    "/js/chunks/412db5785ab3ab60a2f3.js": "/js/chunks/412db5785ab3ab60a2f3.js?id=dee9966e41a94c038fba",
    "/js/chunks/298ac948916e12e22111.js": "/js/chunks/298ac948916e12e22111.js?id=787fa93b8ce4819906dd",
    "/js/chunks/a293460c36d18df60a3b.js": "/js/chunks/a293460c36d18df60a3b.js?id=b605d98aec7a09351b3b",
    "/js/chunks/be71d4b19d32bcbe7249.js": "/js/chunks/be71d4b19d32bcbe7249.js?id=f66c1145c873f8c79079",
    "/js/chunks/a5a05887c156e909a958.js": "/js/chunks/a5a05887c156e909a958.js?id=dbd2f1724bcb31e6e73b",
    "/js/chunks/b60b9234c97acb692433.js": "/js/chunks/b60b9234c97acb692433.js?id=dee9966e41a94c038fba",
    "/js/chunks/caf4058d30883567b9ea.js": "/js/chunks/caf4058d30883567b9ea.js?id=787fa93b8ce4819906dd",
    "/js/chunks/b3bd3c2ba50ccc6c8bac.js": "/js/chunks/b3bd3c2ba50ccc6c8bac.js?id=b605d98aec7a09351b3b",
    "/js/chunks/05562933217c65e69178.js": "/js/chunks/05562933217c65e69178.js?id=f66c1145c873f8c79079",
    "/js/chunks/37bd333b6a05ad92137b.js": "/js/chunks/37bd333b6a05ad92137b.js?id=dbd2f1724bcb31e6e73b",
    "/js/chunks/a4ceca360a20a5e6ff75.js": "/js/chunks/a4ceca360a20a5e6ff75.js?id=dee9966e41a94c038fba",
    "/js/chunks/9ce446426724c8cf56e6.js": "/js/chunks/9ce446426724c8cf56e6.js?id=787fa93b8ce4819906dd",
    "/js/chunks/2a42cf329f93c43cfd16.js": "/js/chunks/2a42cf329f93c43cfd16.js?id=b605d98aec7a09351b3b",
    "/js/chunks/8be95c50a3ba966dbf39.js": "/js/chunks/8be95c50a3ba966dbf39.js?id=f66c1145c873f8c79079",
    "/js/chunks/0fd4fd2d0e72cb32b009.js": "/js/chunks/0fd4fd2d0e72cb32b009.js?id=dbd2f1724bcb31e6e73b",
    "/js/chunks/cf95a44bfcb288f3027b.js": "/js/chunks/cf95a44bfcb288f3027b.js?id=dee9966e41a94c038fba",
    "/js/chunks/bcdebae6efe14a8328d2.js": "/js/chunks/bcdebae6efe14a8328d2.js?id=787fa93b8ce4819906dd",
    "/js/chunks/a5a67fddd75ac3fd3f56.js": "/js/chunks/a5a67fddd75ac3fd3f56.js?id=b605d98aec7a09351b3b",
    "/js/chunks/97e5c90db37588dc89fa.js": "/js/chunks/97e5c90db37588dc89fa.js?id=f66c1145c873f8c79079",
    "/js/chunks/399410fd9a8ebc3dc158.js": "/js/chunks/399410fd9a8ebc3dc158.js?id=dbd2f1724bcb31e6e73b",
    "/js/chunks/7753274d86b5b2a48ba5.js": "/js/chunks/7753274d86b5b2a48ba5.js?id=dee9966e41a94c038fba",
    "/js/chunks/cc52fa06a61bd8c46407.js": "/js/chunks/cc52fa06a61bd8c46407.js?id=787fa93b8ce4819906dd",
    "/js/chunks/8532a39ff8e156f5b386.js": "/js/chunks/8532a39ff8e156f5b386.js?id=b605d98aec7a09351b3b",
    "/js/chunks/d3fee27636bc961ae675.js": "/js/chunks/d3fee27636bc961ae675.js?id=79f4ae21fbbd91e5df38",
    "/js/chunks/7b17039a5400e70f6202.js": "/js/chunks/7b17039a5400e70f6202.js?id=f66c1145c873f8c79079",
    "/js/chunks/1a681df8ead67007865c.js": "/js/chunks/1a681df8ead67007865c.js?id=dbd2f1724bcb31e6e73b",
    "/js/chunks/05c98ec54e6531a25739.js": "/js/chunks/05c98ec54e6531a25739.js?id=dee9966e41a94c038fba",
    "/js/chunks/9ca72abea69631cb1580.js": "/js/chunks/9ca72abea69631cb1580.js?id=787fa93b8ce4819906dd",
    "/js/chunks/bc4937407c55a22bb12a.js": "/js/chunks/bc4937407c55a22bb12a.js?id=b605d98aec7a09351b3b",
    "/js/chunks/14348162e2259aa0e1c6.js": "/js/chunks/14348162e2259aa0e1c6.js?id=a7681b004b8c0770db57",
    "/js/chunks/e77dd8ec3c766ea752d4.js": "/js/chunks/e77dd8ec3c766ea752d4.js?id=d890701341aa0af01f03",
    "/js/chunks/37e13f2242b13f06d60e.js": "/js/chunks/37e13f2242b13f06d60e.js?id=9838938f10a8d196f6b0",
    "/js/chunks/9eb864c9c15f7dc2b7af.js": "/js/chunks/9eb864c9c15f7dc2b7af.js?id=7588397a5913fee47b66",
    "/js/chunks/0516b1880250b5e1aec0.js": "/js/chunks/0516b1880250b5e1aec0.js?id=db497be4bb8fbf721b4b",
    "/js/chunks/58306adde7cbac638690.js": "/js/chunks/58306adde7cbac638690.js?id=250335e4fbd64fdbd475",
    "/js/chunks/6c833a76d296c5961dfa.js": "/js/chunks/6c833a76d296c5961dfa.js?id=757d9197f36a0f9ececb",
    "/js/chunks/787d66bb9e3d61fbbe98.js": "/js/chunks/787d66bb9e3d61fbbe98.js?id=b19b4ce74587628f43cb",
    "/js/chunks/b00ccab2a94217494fce.js": "/js/chunks/b00ccab2a94217494fce.js?id=3d50a99819939b88fa5a",
    "/js/chunks/77dad08b0b9451ad2d6e.js": "/js/chunks/77dad08b0b9451ad2d6e.js?id=a350c9fc6654e6bbb0e2",
    "/js/chunks/56f0b018da19e786c0e5.js": "/js/chunks/56f0b018da19e786c0e5.js?id=95104f4930c570eaa850",
    "/js/chunks/9a337e681d5077279e41.js": "/js/chunks/9a337e681d5077279e41.js?id=95104f4930c570eaa850",
    "/js/chunks/c9088e087145443eea38.js": "/js/chunks/c9088e087145443eea38.js?id=3e832a393b474affaa9e",
    "/js/chunks/c02d8861a14a6931761c.js": "/js/chunks/c02d8861a14a6931761c.js?id=d9f243e361fa6b901f68",
    "/js/chunks/56b8919d1d90a7366e67.js": "/js/chunks/56b8919d1d90a7366e67.js?id=a5552a87e946dfce575f",
    "/js/chunks/0ee69c8845e0bb546977.js": "/js/chunks/0ee69c8845e0bb546977.js?id=d03bad84ba461e13cce2",
    "/js/chunks/b24737cf11aee96b213c.js": "/js/chunks/b24737cf11aee96b213c.js?id=8b5f78acb11add26983d",
    "/js/chunks/f3f44988369b653acc89.js": "/js/chunks/f3f44988369b653acc89.js?id=dd5e4bb4f8b1b48714a4",
    "/js/chunks/7659c9f02bc34adc1e5b.js": "/js/chunks/7659c9f02bc34adc1e5b.js?id=02f12ab5199ae54b213d",
    "/js/chunks/bacccc759ebf1e7ef7cd.js": "/js/chunks/bacccc759ebf1e7ef7cd.js?id=52bfcfd42eda5d72fe99",
    "/js/chunks/0d863e36daa58cfef890.js": "/js/chunks/0d863e36daa58cfef890.js?id=9f8de3a3f52d2b43ef1c",
    "/js/chunks/4843ceda73b42725b1ca.js": "/js/chunks/4843ceda73b42725b1ca.js?id=7a841324dd27b195870c",
    "/js/chunks/d7a1535ad2dc17e5246b.js": "/js/chunks/d7a1535ad2dc17e5246b.js?id=95619b19d37ccce9c58d",
    "/js/chunks/6215620ee88e131556de.js": "/js/chunks/6215620ee88e131556de.js?id=dafec766524af4cfadc7",
    "/js/chunks/e0361de6dcc62e085485.js": "/js/chunks/e0361de6dcc62e085485.js?id=266133dc35344cb29bf7",
    "/js/chunks/8c9500be889dac3761ba.js": "/js/chunks/8c9500be889dac3761ba.js?id=087978c1f12f9839be65",
    "/js/chunks/f895b34ec967e7947622.js": "/js/chunks/f895b34ec967e7947622.js?id=84f009825846ebde81f3",
    "/js/chunks/67789f872c91ebb2d159.js": "/js/chunks/67789f872c91ebb2d159.js?id=715000351f8abee2d2f2",
    "/js/chunks/1a9a0b3fea9b1aecabd3.js": "/js/chunks/1a9a0b3fea9b1aecabd3.js?id=0b3225030247e2aff02c",
    "/js/chunks/a9baf0405600959eb7e4.js": "/js/chunks/a9baf0405600959eb7e4.js?id=53cbf90da130ae961319",
    "/js/chunks/b7318c5d18ab49e123fc.js": "/js/chunks/b7318c5d18ab49e123fc.js?id=7d3ccca331173546b1e5",
    "/js/chunks/43718d1b7a1f4ccfd275.js": "/js/chunks/43718d1b7a1f4ccfd275.js?id=6b36d38529db953720cb",
    "/js/chunks/9aba07af986f56bca0b8.js": "/js/chunks/9aba07af986f56bca0b8.js?id=da561337c0ac230c0a5d",
    "/js/chunks/64c03c03e7bfaa0dd001.js": "/js/chunks/64c03c03e7bfaa0dd001.js?id=46b0e311daec57655aff",
    "/js/chunks/070df68a58ed9d741a8d.js": "/js/chunks/070df68a58ed9d741a8d.js?id=fc1340c447e576a62007",
    "/js/chunks/6fa17acc1a755a0ccfe7.js": "/js/chunks/6fa17acc1a755a0ccfe7.js?id=9286ff7278dbb056f858",
    "/js/chunks/48687e5a1d1cbe6646ad.js": "/js/chunks/48687e5a1d1cbe6646ad.js?id=66393ad61b82ff28f179",
    "/js/chunks/de989adccfa0f9fec61b.js": "/js/chunks/de989adccfa0f9fec61b.js?id=f47a118c293e7182e54b",
    "/js/chunks/fcc604ded757e1f6b7f8.js": "/js/chunks/fcc604ded757e1f6b7f8.js?id=b90e7d5ae1663b36ac27",
    "/js/chunks/bff4c963f3510665f137.js": "/js/chunks/bff4c963f3510665f137.js?id=fa7539badd26abd76a11",
    "/js/chunks/824df03d37ec146d75dc.js": "/js/chunks/824df03d37ec146d75dc.js?id=72755aa5717b016f6d1d",
    "/js/chunks/696fd542a7cd8135e224.js": "/js/chunks/696fd542a7cd8135e224.js?id=193f530de8da298e1010",
    "/js/chunks/3577685cfe935003954d.js": "/js/chunks/3577685cfe935003954d.js?id=16ada7bf97fec3186f76",
    "/js/chunks/d7bcffccb73f5a33d00f.js": "/js/chunks/d7bcffccb73f5a33d00f.js?id=736adaac08c0c25dc230",
    "/js/chunks/537f3b96e9de7e7a2885.js": "/js/chunks/537f3b96e9de7e7a2885.js?id=06b80fd2f41b9aa938ef",
    "/js/chunks/73245d4b4ba83eacd93e.js": "/js/chunks/73245d4b4ba83eacd93e.js?id=e68235a5a544e3dc4857",
    "/js/chunks/5618bbd73d1c1c9130b0.js": "/js/chunks/5618bbd73d1c1c9130b0.js?id=1e2e0066bb01b7f475d1",
    "/js/chunks/b9d6d4b9df39fa2e5b6e.js": "/js/chunks/b9d6d4b9df39fa2e5b6e.js?id=4677967c4c5b53eed394",
    "/js/chunks/89d9422b6ed1f758787e.js": "/js/chunks/89d9422b6ed1f758787e.js?id=ff3754b225f08e519657",
    "/js/chunks/7961df9b6550e44ebe15.js": "/js/chunks/7961df9b6550e44ebe15.js?id=2223cba4b696fba49ecf",
    "/js/chunks/f925435fcb8fe40d7b09.js": "/js/chunks/f925435fcb8fe40d7b09.js?id=18399140d361264147f3",
    "/js/chunks/9d179ee5ff02d42e103c.js": "/js/chunks/9d179ee5ff02d42e103c.js?id=3a77a3df1deddf027324",
    "/js/chunks/7ac92b62bf349237f57a.js": "/js/chunks/7ac92b62bf349237f57a.js?id=58faf4a3e646566b47d4",
    "/js/chunks/6c5307b82bf29bfdadf5.js": "/js/chunks/6c5307b82bf29bfdadf5.js?id=251a82a0f9b9e8f8c2f1",
    "/js/chunks/269bf07866f295decbb2.js": "/js/chunks/269bf07866f295decbb2.js?id=234101c0c38fa1b4af81",
    "/js/chunks/2ee6126fd68117af765c.js": "/js/chunks/2ee6126fd68117af765c.js?id=26150f37de47ede8cdf2",
    "/js/chunks/70c17298cc1a4a255812.js": "/js/chunks/70c17298cc1a4a255812.js?id=d82d66c8b5786b1519b1",
    "/js/chunks/dde9992e98b7d0adb66c.js": "/js/chunks/dde9992e98b7d0adb66c.js?id=04d277d53896b3cac3aa",
    "/js/chunks/a7cd2ce5759400eada4b.js": "/js/chunks/a7cd2ce5759400eada4b.js?id=9af5197c3eb93159e938",
    "/js/chunks/23e36f08723e927fdf95.js": "/js/chunks/23e36f08723e927fdf95.js?id=9715823ae4bb9995c7ec",
    "/js/chunks/b529783a61ae01eeba03.js": "/js/chunks/b529783a61ae01eeba03.js?id=d04a1d3d3fba514516f2",
    "/js/chunks/689b7124afc59dbd8bb3.js": "/js/chunks/689b7124afc59dbd8bb3.js?id=8151d5e0a5cd8e3579e8",
    "/js/chunks/0c88a59594e014eb95b6.js": "/js/chunks/0c88a59594e014eb95b6.js?id=a9e631fbd26118dcce06",
    "/js/chunks/807894db970e942d0b9f.js": "/js/chunks/807894db970e942d0b9f.js?id=f695005e41d69e9af5c8",
    "/js/chunks/5bad8d20e30a45f123f8.js": "/js/chunks/5bad8d20e30a45f123f8.js?id=694fb898ca8519082f4d",
    "/js/chunks/b4467a734be25d77565c.js": "/js/chunks/b4467a734be25d77565c.js?id=e65ffd738d95beab77f3",
    "/js/chunks/fe0e2573491afe9acacd.js": "/js/chunks/fe0e2573491afe9acacd.js?id=575b8ae25ced8388d26f",
    "/js/chunks/09df33e963f83441a094.js": "/js/chunks/09df33e963f83441a094.js?id=9ba0897c3e3d87fcbfde",
    "/js/chunks/2b408d3ff3ffbaf850ae.js": "/js/chunks/2b408d3ff3ffbaf850ae.js?id=9249aced5d3b481d6083",
    "/js/chunks/bf6c59dc3dafb68fe140.js": "/js/chunks/bf6c59dc3dafb68fe140.js?id=99c9d9e72f164ad22801",
    "/js/chunks/b9a3aea65a6c0925b512.js": "/js/chunks/b9a3aea65a6c0925b512.js?id=137c744792d74099f7c0",
    "/js/chunks/7631f1208533d2397bc5.js": "/js/chunks/7631f1208533d2397bc5.js?id=23037e87354e8108e4ac",
    "/js/chunks/687a69d15bd342615bae.js": "/js/chunks/687a69d15bd342615bae.js?id=23037e87354e8108e4ac",
    "/js/chunks/33bc0881a31c3e633fd7.js": "/js/chunks/33bc0881a31c3e633fd7.js?id=1a3d126b5c75c441a473",
    "/js/chunks/943d854304faa1d82bc4.js": "/js/chunks/943d854304faa1d82bc4.js?id=8747675346d7982ff41f",
    "/js/chunks/a7481f0ed382d2e9ad47.js": "/js/chunks/a7481f0ed382d2e9ad47.js?id=58284a1c9ce3d34588a8",
    "/js/chunks/3432569e72cc17d74e4a.js": "/js/chunks/3432569e72cc17d74e4a.js?id=4ca7cbcfd10f3c53d0cf",
    "/js/chunks/17a90e0c866be92be11c.js": "/js/chunks/17a90e0c866be92be11c.js?id=84821317cfeb6a34d594",
    "/js/chunks/539f267774635aaf146b.js": "/js/chunks/539f267774635aaf146b.js?id=035916ff221b88f998f3",
    "/js/chunks/2e8669f92ac3768de414.js": "/js/chunks/2e8669f92ac3768de414.js?id=e57c76859b5f8541f81d",
    "/js/chunks/280a24d1181b864991d9.js": "/js/chunks/280a24d1181b864991d9.js?id=f3a7fd50377142b246c4",
    "/js/chunks/aea825670fa5ba5b06b9.js": "/js/chunks/aea825670fa5ba5b06b9.js?id=00c49b0bc62383173f73",
    "/js/chunks/23dfa1b7c43f8c344a55.js": "/js/chunks/23dfa1b7c43f8c344a55.js?id=a2b4df401a659da30289",
    "/js/chunks/477688c1572df1e2912a.js": "/js/chunks/477688c1572df1e2912a.js?id=143c84be83abf1ee821d",
    "/js/chunks/75ed864e7a6fd9a74bb4.js": "/js/chunks/75ed864e7a6fd9a74bb4.js?id=0078360c530be14231c1",
    "/js/chunks/e7e052d8d3d04ff83313.js": "/js/chunks/e7e052d8d3d04ff83313.js?id=9130f465c289cc31a9ea",
    "/js/chunks/879e2dc0428f12550920.js": "/js/chunks/879e2dc0428f12550920.js?id=5e28f622148b6460312d",
    "/js/chunks/abda712dc9713d94c7b7.js": "/js/chunks/abda712dc9713d94c7b7.js?id=83ed8d1fe37df073403d",
    "/js/chunks/adb3cb728814fe9a62d6.js": "/js/chunks/adb3cb728814fe9a62d6.js?id=d41db9a6da081d8629ad",
    "/js/chunks/76919c87f0debe622dd0.js": "/js/chunks/76919c87f0debe622dd0.js?id=fff4994de3c762f665b7",
    "/js/chunks/208d8eef9ae428d3e8ae.js": "/js/chunks/208d8eef9ae428d3e8ae.js?id=87052a1d34b1bd81681d",
    "/js/chunks/65373aac51d4ae1d61a1.js": "/js/chunks/65373aac51d4ae1d61a1.js?id=a8292c4d10c0e3074fca",
    "/js/chunks/c4b9bdb31cd436c1ea57.js": "/js/chunks/c4b9bdb31cd436c1ea57.js?id=b0399a11684d29b0c7d6",
    "/js/chunks/f32cec7a0f51b6033299.js": "/js/chunks/f32cec7a0f51b6033299.js?id=f17170db80dafd7fe4c0",
    "/js/chunks/4b9a6b2301e7ee185228.js": "/js/chunks/4b9a6b2301e7ee185228.js?id=25f2980b3ad1ea573712",
    "/js/chunks/0bf83c74e375bc656fa0.js": "/js/chunks/0bf83c74e375bc656fa0.js?id=3413c5eede1e5db8612c",
    "/js/chunks/7f72ffbdc4e9a3f0157e.js": "/js/chunks/7f72ffbdc4e9a3f0157e.js?id=f60b1cb5b4a9d5d89f75",
    "/js/chunks/b0724902f21c75246940.js": "/js/chunks/b0724902f21c75246940.js?id=cd95c372e1ca39f2ab8c",
    "/js/chunks/f58bb2e074aa8ba8673d.js": "/js/chunks/f58bb2e074aa8ba8673d.js?id=1f9dc9f75281b6f485dd",
    "/js/chunks/af3ed8ff545c446437d6.js": "/js/chunks/af3ed8ff545c446437d6.js?id=7e50fa34e9eed5f56866",
    "/js/chunks/5d9bf6b29cf350dfe92b.js": "/js/chunks/5d9bf6b29cf350dfe92b.js?id=32b9175a1257cac113d9",
    "/js/chunks/b47e01d6b22343d9dff4.js": "/js/chunks/b47e01d6b22343d9dff4.js?id=543810a796d4f6093c58",
    "/js/chunks/da0244f83da2c030c8e0.js": "/js/chunks/da0244f83da2c030c8e0.js?id=a190808adc32bee46428",
    "/js/chunks/c3791f955e357e9d99e9.js": "/js/chunks/c3791f955e357e9d99e9.js?id=de421a66d9b371ef5a5d",
    "/js/chunks/fe13358d0fab9f3410c1.js": "/js/chunks/fe13358d0fab9f3410c1.js?id=56d05b177df1b79afc83",
    "/js/chunks/908de838941c592f8f4b.js": "/js/chunks/908de838941c592f8f4b.js?id=c1fe2fcf5ae4395b7945",
    "/js/chunks/469774a3bc73aa623dd6.js": "/js/chunks/469774a3bc73aa623dd6.js?id=c1fe2fcf5ae4395b7945",
    "/js/chunks/be20559150b47987dc3b.js": "/js/chunks/be20559150b47987dc3b.js?id=f74f49c7908ceb8b5f1d",
    "/js/chunks/0d6439d18c2c70aa8dc5.js": "/js/chunks/0d6439d18c2c70aa8dc5.js?id=7d6a8e452389ede5a3ca",
    "/js/chunks/284557e22c8044b11b2d.js": "/js/chunks/284557e22c8044b11b2d.js?id=a9eb5132f0942dd4acd4",
    "/js/chunks/5c3d23e1ae6a892c19ba.js": "/js/chunks/5c3d23e1ae6a892c19ba.js?id=04f2534d8c9caca9edaa",
    "/js/chunks/de400308ef17f6ace374.js": "/js/chunks/de400308ef17f6ace374.js?id=b9373f0e6aa52f25b402",
    "/js/chunks/c0669069de9282f51308.js": "/js/chunks/c0669069de9282f51308.js?id=9f512dcc6dbacb92a748",
    "/js/chunks/d4657c7c2a01a734bd03.js": "/js/chunks/d4657c7c2a01a734bd03.js?id=f48d929dad4db7efcb42",
    "/js/chunks/f72efa0ddf92b45cece5.js": "/js/chunks/f72efa0ddf92b45cece5.js?id=cae422c10e64f45f8a40",
    "/js/chunks/5fb3ce6b9275493a1eb9.js": "/js/chunks/5fb3ce6b9275493a1eb9.js?id=cae422c10e64f45f8a40",
    "/js/chunks/2e9d1e6fe264f8c7ad4d.js": "/js/chunks/2e9d1e6fe264f8c7ad4d.js?id=3ce68cad8f83045b0fc1",
    "/js/chunks/03cfccf3f74990971726.js": "/js/chunks/03cfccf3f74990971726.js?id=41744ddcbc95c540f5b8",
    "/js/chunks/5acae14f407eb888121c.js": "/js/chunks/5acae14f407eb888121c.js?id=21e2424ab8bca6d63a8b",
    "/js/chunks/0eb96ac9302f2b5cf022.js": "/js/chunks/0eb96ac9302f2b5cf022.js?id=5e6fccd7063f02caea99",
    "/js/chunks/68b24628e4cdb39f8c81.js": "/js/chunks/68b24628e4cdb39f8c81.js?id=5056c5bf7d4d6032561f",
    "/js/chunks/5e563cb43c8991e03aa5.js": "/js/chunks/5e563cb43c8991e03aa5.js?id=fe48553ce8c956bdb375",
    "/js/chunks/a4746235ee68229b0dd8.js": "/js/chunks/a4746235ee68229b0dd8.js?id=496e1719cc791a430cc0"
}
